langchain_timbr/__init__.py
langchain_timbr/_version.py
langchain_timbr/config.py
langchain_timbr/timbr_llm_connector.py
langchain_timbr/langchain/__init__.py
langchain_timbr/langchain/execute_timbr_query_chain.py
langchain_timbr/langchain/generate_answer_chain.py
langchain_timbr/langchain/generate_timbr_sql_chain.py
langchain_timbr/langchain/identify_concept_chain.py
langchain_timbr/langchain/timbr_sql_agent.py
langchain_timbr/langchain/validate_timbr_sql_chain.py
langchain_timbr/langgraph/__init__.py
langchain_timbr/langgraph/execute_timbr_query_node.py
langchain_timbr/langgraph/generate_response_node.py
langchain_timbr/langgraph/generate_timbr_sql_node.py
langchain_timbr/langgraph/identify_concept_node.py
langchain_timbr/langgraph/validate_timbr_query_node.py
langchain_timbr/llm_wrapper/llm_wrapper.py
langchain_timbr/llm_wrapper/timbr_llm_wrapper.py
langchain_timbr/utils/general.py
langchain_timbr/utils/prompt_service.py
langchain_timbr/utils/temperature_supported_models.json
langchain_timbr/utils/timbr_llm_utils.py
langchain_timbr/utils/timbr_utils.py
langchain_timbr-2.2.0.dist-info/METADATA
langchain_timbr-2.2.0.dist-info/WHEEL
langchain_timbr-2.2.0.dist-info/licenses/LICENSE
langchain_timbr-2.2.0.dist-info/RECORD
